LICENSE.md
MANIFEST.in
requirements.txt
setup.py
Flask_SQLSoup.egg-info/PKG-INFO
Flask_SQLSoup.egg-info/SOURCES.txt
Flask_SQLSoup.egg-info/dependency_links.txt
Flask_SQLSoup.egg-info/not-zip-safe
Flask_SQLSoup.egg-info/requires.txt
Flask_SQLSoup.egg-info/top_level.txt
flask_sqlsoup/__init__.py