Metadata-Version: 1.1
Name: Flask-SQLSoup
Version: 0.1.0
Summary: Makes it simpler to use SQLSoup with Flask
Home-page: http://github.com/singularita/flask-sqlsoup/
Author: Singularita s.r.o.
Author-email: UNKNOWN
License: MIT
Keywords: utilities
Platform: UNKNOWN
Classifier: Development Status :: 2 - Pre-Alpha
Classifier: Programming Language :: Python :: 3 :: Only
Classifier: License :: OSI Approved :: MIT License
Classifier: Intended Audience :: Developers
